{
  "ticker": "TSM",
  "company_name": "Taiwan Semiconductor Manufacturing Company Limited",
  "valuation_date": "2026-01-22",
  "current_price": 326.12,
  "currency": "USD",
  "note": "Prices in USD per ADR (1 ADR = 5 ordinary shares). Financial data converted from NT$ at 32:1.",
  "inputs": {
    "shares_outstanding_adr": 5186.4,
    "shares_outstanding_ordinary": 25932.0,
    "adr_ratio": 5,
    "net_debt": -36537.0,
    "net_cash": 36537.0,
    "last_fcf": 27194.0,
    "last_revenue": 90447.0,
    "last_net_income": 36172.0,
    "fcf_margin_fy2024": 30.1,
    "units": "millions USD",
    "exchange_rate": 32.0
  },
  "historical_growth": {
    "revenue_3yr_cagr": 22.17,
    "revenue_5yr_cagr": 22.02,
    "revenue_10yr_cagr": 14.27,
    "eps_3yr_cagr": 25.07,
    "eps_5yr_cagr": 26.76,
    "eps_10yr_cagr": 16.37,
    "equity_1yr_growth": 23.9,
    "fcf_3yr_cagr": 47.17,
    "fcf_5yr_cagr": 41.26,
    "selected_growth_rate": 22.0,
    "growth_rate_source": "revenue_5yr_cagr",
    "growth_divergence_warning": "Historical growth very strong. FCF 5yr CAGR of 41% reflects operational leverage."
  },
  "assumptions": {
    "base": {
      "growth_rates": [
        28,
        22,
        18,
        15,
        12
      ],
      "fcf_margin": 35.0,
      "wacc": 10.5,
      "terminal_growth": 4.0,
      "description": "Management guidance achieved, strong execution continues"
    },
    "bull": {
      "growth_rates": [
        30,
        28,
        22,
        18,
        15
      ],
      "fcf_margin": 38.0,
      "wacc": 9.5,
      "terminal_growth": 4.5,
      "description": "AI super-cycle extends through 2030+, TSM maintains dominance"
    },
    "bear": {
      "growth_rates": [
        18,
        12,
        10,
        8,
        6
      ],
      "fcf_margin": 28.0,
      "wacc": 12.5,
      "terminal_growth": 3.0,
      "description": "AI demand moderates, geopolitical tensions increase"
    }
  },
  "projections": {
    "base": {
      "years": [
        2025,
        2026,
        2027,
        2028,
        2029
      ],
      "revenue": [
        115772.0,
        141242.0,
        166665.0,
        191665.0,
        214665.0
      ],
      "fcf": [
        40520.0,
        49435.0,
        58333.0,
        67083.0,
        75133.0
      ],
      "discount_factors": [
        0.905,
        0.819,
        0.7412,
        0.6707,
        0.607
      ],
      "pv_fcf": [
        36670.0,
        40486.0,
        43234.0,
        44995.0,
        45606.0
      ]
    },
    "bull": {
      "years": [
        2025,
        2026,
        2027,
        2028,
        2029
      ],
      "revenue": [
        117581.0,
        150504.0,
        183614.0,
        216665.0,
        249165.0
      ],
      "fcf": [
        44681.0,
        57191.0,
        69773.0,
        82333.0,
        94683.0
      ],
      "discount_factors": [
        0.9132,
        0.834,
        0.7617,
        0.6956,
        0.6352
      ],
      "pv_fcf": [
        40804.0,
        47698.0,
        53143.0,
        57269.0,
        60145.0
      ]
    },
    "bear": {
      "years": [
        2025,
        2026,
        2027,
        2028,
        2029
      ],
      "revenue": [
        106727.0,
        119535.0,
        131488.0,
        142007.0,
        150528.0
      ],
      "fcf": [
        29884.0,
        33470.0,
        36817.0,
        39762.0,
        42148.0
      ],
      "discount_factors": [
        0.8889,
        0.7901,
        0.7023,
        0.6243,
        0.5549
      ],
      "pv_fcf": [
        26563.0,
        26445.0,
        25858.0,
        24823.0,
        23389.0
      ]
    }
  },
  "valuation": {
    "base": {
      "sum_pv_fcf": 210991.0,
      "terminal_value": 1202124.0,
      "pv_terminal": 729689.0,
      "enterprise_value": 940680.0,
      "equity_value": 977217.0,
      "intrinsic_value": 188.42,
      "upside": -42.2
    },
    "bull": {
      "sum_pv_fcf": 259059.0,
      "terminal_value": 1978866.0,
      "pv_terminal": 1257031.0,
      "enterprise_value": 1516090.0,
      "equity_value": 1552627.0,
      "intrinsic_value": 299.37,
      "upside": -8.2
    },
    "bear": {
      "sum_pv_fcf": 127078.0,
      "terminal_value": 456970.0,
      "pv_terminal": 253586.0,
      "enterprise_value": 380664.0,
      "equity_value": 417201.0,
      "intrinsic_value": 80.44,
      "upside": -75.3
    }
  },
  "entry_price": {
    "base": {
      "terminal_value_per_share": 231.78,
      "years_to_terminal": 5,
      "target_cagr": 15.0,
      "entry_price": 115.24,
      "entry_discount_from_current": -64.7
    },
    "bull": {
      "terminal_value_per_share": 381.55,
      "years_to_terminal": 5,
      "target_cagr": 15.0,
      "entry_price": 189.7,
      "entry_discount_from_current": -41.8
    },
    "bear": {
      "terminal_value_per_share": 88.11,
      "years_to_terminal": 5,
      "target_cagr": 15.0,
      "entry_price": 43.81,
      "entry_discount_from_current": -86.6
    }
  },
  "sensitivity": {
    "wacc_range": [
      8.5,
      9.5,
      10.5,
      11.5,
      12.5
    ],
    "terminal_growth_range": [
      3.0,
      3.5,
      4.0,
      4.5,
      5.0
    ],
    "matrix": [
      [
        230.54,
        249.54,
        272.77,
        301.81,
        339.14
      ],
      [
        194.71,
        207.63,
        222.9,
        241.22,
        263.61
      ],
      [
        168.49,
        177.74,
        188.42,
        200.88,
        215.6
      ],
      [
        148.47,
        155.36,
        163.17,
        172.1,
        182.4
      ],
      [
        132.69,
        137.98,
        143.89,
        150.54,
        158.08
      ]
    ],
    "description": "Intrinsic value per ADR under different WACC and terminal growth assumptions (Base Case projections)"
  },
  "probability_weighted": {
    "weights": {
      "bull": 0.3,
      "base": 0.5,
      "bear": 0.2
    },
    "weighted_iv": 200.11,
    "upside_to_weighted": -38.6
  },
  "interpretation": {
    "valuation_verdict": "Overvalued at current price",
    "market_implies": "Market is pricing in growth rates exceeding even the bull case, suggesting high expectations for AI super-cycle sustainability",
    "key_insights": [
      "TSM trading at $326.12 vs Base Case IV of $188.42 (-42% downside)",
      "Even in Bull Case (30% growth Y1-Y2, 38% FCF margins), IV is $299.37 (-8% downside)",
      "Current P/E of 46.8x is significantly elevated for a semiconductor manufacturer",
      "Probability-weighted IV of $200 suggests 39% downside risk from current levels",
      "Entry price for 15% CAGR in Base Case is $115 (65% below current)",
      "Market is pricing in sustained AI boom with minimal cyclical risk"
    ],
    "risks": [
      "Geopolitical risk (Taiwan-China tensions) not fully priced in",
      "AI demand cyclicality - any moderation would trigger severe multiple compression",
      "Customer concentration (Apple 22%, NVIDIA 12%, Top 10 = 76%)",
      "Massive capex requirements ($50B+ annually) strain cash flow",
      "Valuation leaves no margin of safety for execution missteps"
    ],
    "catalysts_for_rerating": [
      "Continued AI accelerator demand exceeding 50%+ CAGR expectations",
      "N2 (2nm) technology ramp ahead of schedule with premium pricing",
      "Geographic diversification reducing Taiwan risk premium",
      "Operating margin expansion from scale and advanced node mix",
      "Resolution of geopolitical tensions"
    ]
  },
  "methodology_notes": {
    "fcf_margin_assumptions": "FY2024 FCF margin of 30% reflects massive growth capex ($30B). Projections assume capex moderates as facilities come online, improving FCF margins to 28-38% range.",
    "wacc_justification": "9.5-12.5% range reflects geopolitical risk premium. Lower end assumes Taiwan tensions ease; higher end reflects current elevated risk.",
    "terminal_growth_rationale": "3-4.5% terminal growth reflects semiconductor industry growth plus TSM's technology leadership position enabling above-GDP growth.",
    "scenario_probabilities": "Bull 30%, Base 50%, Bear 20% - weighted toward positive outcomes given TSM's execution track record and AI tailwinds, but with meaningful bear case probability.",
    "net_cash_benefit": "$36.5B net cash position (negative net debt) adds value per share and provides buffer for capex."
  }
}